kahi_elasticsearch_works/Kahi_elasticsearch_works.py
kahi_elasticsearch_works/__init__.py
kahi_elasticsearch_works/_version.py
Kahi_elasticsearch_works-0.1.0b0.dist-info/LICENSE
Kahi_elasticsearch_works-0.1.0b0.dist-info/METADATA
Kahi_elasticsearch_works-0.1.0b0.dist-info/WHEEL
Kahi_elasticsearch_works-0.1.0b0.dist-info/top_level.txt
Kahi_elasticsearch_works-0.1.0b0.dist-info/RECORD
