Metadata-Version: 2.1
Name: Kahi_elasticsearch_works
Version: 0.1.0b0
Summary: Kahi plugin to insert and update works to elasticsearch
Home-page: https://github.com/colav/Kahi_plugins
Author: Colav
Author-email: colav@udea.edu.co
License: BSD
License-File: LICENSE
Requires-Dist: kahi
Requires-Dist: pymongo
Requires-Dist: mohan
